Workbook

Sheet Summary Dashboard
A1: GOLD ETF PORTFOLIO DASHBOARD | J1: AUTOMATION & SOURCES
J2: Automation | K2: Daily price pull + formula update
A3: Latest Trading Date | C3: Portfolio Value | E3: 1-Day Change | G3: Change vs First Day | I3: Physical Gold (10g) | K3: Yahoo Finance / yfinance
A4: =LOOKUP(2,1/(Dashboard!A:A<>""),Dashboard!A:A) | C4: =LOOKUP(2,1/(Dashboard!C:C<>""),Dashboard!C:C)+LOOKUP(2,1/(Dashboard!E:E<>""),Dashboard!E:E)+LOOKUP(2,1/(Dashboard!G:G<>""),Dashboard!G:G)+LOOKUP(2,1/(Dashboard!I:I<>""),Dashboard!I:I)+LOOKUP(2,1/(Dashboard!K:K<>""),Dashboard!K:K) | E4: =C4 - (INDEX(Dashboard!C:C, MATCH(9.99E+307,Dashboard!C:C)-1)+INDEX(Dashboard!E:E, MATCH(9.99E+307,Dashboard!E:E)-1)+INDEX(Dashboard!G:G, MATCH(9.99E+307,Dashboard!G:G)-1)+INDEX(Dashboard!I:I, MATCH(9.99E+307,Dashboard!I:I)-1)+INDEX(Dashboard!K:K, MATCH(9.99E+307,Dashboard!K:K)-1)) | G4: =C4 - (Dashboard!C2+Dashboard!E2+Dashboard!G2+Dashboard!I2+Dashboard!K2) | I4: =LOOKUP(2,1/(Dashboard!L:L<>""),Dashboard!L:L) | K4: GOLDBETA 2356 | HDFCGOLD 1934 | GOLDIETF 1544 | BSLGOLDETF 1111 | LICMFGOLD 733
A6: ETF | B6: Latest Price | C6: Holding Value | D6: Weight % | E6: 1D Change | F6: 1D Change % | G6: NAV Change
A7: GOLDBETA | B7: =LOOKUP(2,1/(Dashboard!B:B<>""),Dashboard!B:B) | C7: =LOOKUP(2,1/(Dashboard!C:C<>""),Dashboard!C:C) | D7: =C7/C$4 | E7: =C7 - INDEX(Dashboard!C:C, MATCH(9.99E+307,Dashboard!C:C)-1) | F7: =E7 / INDEX(Dashboard!C:C, MATCH(9.99E+307,Dashboard!C:C)-1) | G7: =LOOKUP(2,1/(GOLDBETA!D:D<>""),GOLDBETA!D:D) - INDEX(GOLDBETA!D:D, MATCH(9.99E+307,GOLDBETA!D:D)-1)
A8: HDFCGOLD | B8: =LOOKUP(2,1/(Dashboard!D:D<>""),Dashboard!D:D) | C8: =LOOKUP(2,1/(Dashboard!E:E<>""),Dashboard!E:E) | D8: =C8/C$4 | E8: =C8 - INDEX(Dashboard!E:E, MATCH(9.99E+307,Dashboard!E:E)-1) | F8: =E8 / INDEX(Dashboard!E:E, MATCH(9.99E+307,Dashboard!E:E)-1) | G8: =LOOKUP(2,1/(HDFCGOLD!D:D<>""),HDFCGOLD!D:D) - INDEX(HDFCGOLD!D:D, MATCH(9.99E+307,HDFCGOLD!D:D)-1)
A9: GOLDIETF | B9: =LOOKUP(2,1/(Dashboard!F:F<>""),Dashboard!F:F) | C9: =LOOKUP(2,1/(Dashboard!G:G<>""),Dashboard!G:G) | D9: =C9/C$4 | E9: =C9 - INDEX(Dashboard!G:G, MATCH(9.99E+307,Dashboard!G:G)-1) | F9: =E9 / INDEX(Dashboard!G:G, MATCH(9.99E+307,Dashboard!G:G)-1) | G9: =LOOKUP(2,1/(GOLDIETF!D:D<>""),GOLDIETF!D:D) - INDEX(GOLDIETF!D:D, MATCH(9.99E+307,GOLDIETF!D:D)-1)
A10: BSLGOLDETF | B10: =LOOKUP(2,1/(Dashboard!H:H<>""),Dashboard!H:H) | C10: =LOOKUP(2,1/(Dashboard!I:I<>""),Dashboard!I:I) | D10: =C10/C$4 | E10: =C10 - INDEX(Dashboard!I:I, MATCH(9.99E+307,Dashboard!I:I)-1) | F10: =E10 / INDEX(Dashboard!I:I, MATCH(9.99E+307,Dashboard!I:I)-1) | G10: =LOOKUP(2,1/(BSLGOLDETF!D:D<>""),BSLGOLDETF!D:D) - INDEX(BSLGOLDETF!D:D, MATCH(9.99E+307,BSLGOLDETF!D:D)-1)
A11: LICMFGOLD | B11: =LOOKUP(2,1/(Dashboard!J:J<>""),Dashboard!J:J) | C11: =LOOKUP(2,1/(Dashboard!K:K<>""),Dashboard!K:K) | D11: =C11/C$4 | E11: =C11 - INDEX(Dashboard!K:K, MATCH(9.99E+307,Dashboard!K:K)-1) | F11: =E11 / INDEX(Dashboard!K:K, MATCH(9.99E+307,Dashboard!K:K)-1) | G11: =LOOKUP(2,1/(LICMFGOLD!D:D<>""),LICMFGOLD!D:D) - INDEX(LICMFGOLD!D:D, MATCH(9.99E+307,LICMFGOLD!D:D)-1)
A12: TOTAL | C12: =SUM(C7:C11) | D12: 1 | E12: =SUM(E7:E11) | F12: =E12 / (C12 - E12)

Sheet Dashboard
A1: Date | B1: GOLDBETA Close | C1: GOLDBETA Value | D1: HDFCGOLD Close | E1: HDFCGOLD Value | F1: GOLDIETF Close | G1: GOLDIETF Value | H1: BSLGOLDETF Close | I1: BSLGOLDETF Value | J1: LICMFGOLD Close | K1: LICMFGOLD Value | L1: Physical Gold (10g) ₹
A2: 46272 | B2: 128 | C2: 301568 | D2: 129.88 | E2: 251187.92 | F2: 130.01 | G2: 200735.44 | H2: 133.82 | I2: 148674.02 | J2: 137.1 | K2: 100494.3 | L2: 160985.14
A3: 46273 | B3: 128.15 | C3: 301921.4 | D3: 130.18 | E3: 251768.12 | F3: 130.38 | G3: 201306.72 | H3: 133.97 | I3: 148840.67 | J3: 137.2 | K3: 100567.6 | L3: 159737.12
A4: 46274 | B4: 128.25 | C4: 302157 | D4: 130.06 | E4: 251536.04 | F4: 130.37 | G4: 201291.28 | H4: 133.98 | I4: 148851.78 | J4: 136.9 | K4: 100347.7 | L4: 161080.45
A5: 46275 | B5: 128.5 | C5: 302746 | D5: 130.49 | E5: 252367.66 | F5: 130.75 | G5: 201878 | H5: 134.33 | I5: 149240.63 | J5: 137.2 | K5: 100567.6 | L5: 159636.84
A6: 46276 | B6: 127.5 | C6: 300390 | D6: 129.37 | E6: 250201.58 | F6: 129.63 | G6: 200148.72 | H6: 133.25 | I6: 148040.75 | J6: 136.3 | K6: 99907.9 | L6: 160673.17
A7: 46280 | B7: 126.05 | C7: 296973.8 | D7: 127.88 | E7: 247319.92 | F7: 127.94 | G7: 197539.36 | H7: 131.88 | I7: 146518.68 | J7: 133.95 | K7: 98185.35 | L7: 158132.35
A8: 46281 | B8: 127.15 | C8: 299565.4 | D8: 129.11 | E8: 249698.74 | F8: 129.44 | G8: 199855.36 | H8: 132.9 | I8: 147651.9 | J8: 135.6 | K8: 99394.8 | L8: 160391.54
A9: 46282 | B9: 126.85 | C9: 298858.6 | D9: 128.68 | E9: 248867.12 | F9: 128.97 | G9: 199129.68 | H9: 132.57 | I9: 147285.27 | J9: 135.3 | K9: 99174.9 | L9: 161071.44
A10: 46283 | B10: 128.6 | C10: 302981.6 | D10: 130.64 | E10: 252657.76 | F10: 131.16 | G10: 202511.04 | H10: 134.53 | I10: 149462.83 | J10: 137.65 | K10: 100897.45 | L10: 161432.68
A11: 46286 | B11: 127.9 | C11: 301332.4 | D11: 129.83 | E11: 251091.22 | F11: 130.01 | G11: 200735.44 | H11: 133.72 | I11: 148562.92 | J11: 137.1 | K11: 100494.3 | L11: 160141
A12: 46287 | B12: 127.25 | C12: 299801 | D12: 129.26 | E12: 249988.84 | F12: 129.42 | G12: 199824.48 | H12: 133.06 | I12: 147829.66 | J12: 135.8 | K12: 99541.4 | L12: 159370.74
A13: 46288 | B13: 127.1 | C13: 299447.6 | D13: 128.94 | E13: 249369.96 | F13: 129.21 | G13: 199500.24 | H13: 132.9 | I13: 147651.9 | J13: 135.9 | K13: 99614.7 | L13: 158230.15
... A15: 46290 | B15: 126.65 | C15: 298387.4 | D15: 128.63 | E15: 248770.42 | F15: 129.03 | G15: 199222.32 | H15: 132.4 | I15: 147096.4 | J15: 135.7 | K15: 99468.1 | L15: 158193.08

Sheet GOLDBETA
A1: UTI Gold Exchange Traded Fund (GOLDBETA.NS) — Daily Tracker
A3: Fund | B3: UTI Gold Exchange Traded Fund | D3: Notes | E3: Daily NAV values updated from the user-supplied UTI Mutual Fund / AMFI extract: ₹127.3391 on 07-Sep-2026 through ₹128.2152 on 18-Sep-2026. Market close source: Yahoo Finance. TD values were not reliably reported.
A4: Yahoo symbol | B4: GOLDBETA.NS
A5: TER (periodic) | B5: 0.0059
A6: TER as of | B6: 2026-09-18
A7: TD 1Y (periodic)
A8: TD 3Y (periodic) | B8: Daily public series available (UTI/AMFI extract supplied by user)
A9: TD as of | B9: Not publicly reported
A10: Date | B10: Day | C10: Market Close (₹) | D10: NAV (₹) | E10: Premium/(Discount) to NAV % | F10: TER % (periodic) | G10: TER As Of | H10: TD 1Y % (periodic) | I10: TD 3Y % (periodic) | J10: TD As Of | K10: Market Data Status | L10: NAV Data Status
A11: 46272 | B11: Mon | C11: 128 | D11: 127.3391 | E11: =IFERROR(C11/D11-1,"") | F11: 0.0059 | G11: 2026-09-18 | J11: Not publicly reported | K11: Available | L11: Available
A12: 46273 | B12: Tue | C12: 128.15 | D12: 127.6657 | E12: =IFERROR(C12/D12-1,"") | F12: 0.0059 | G12: 2026-09-18 | J12: Not publicly reported | K12: Available | L12: Available
A13: 46274 | B13: Wed | C13: 128.25 | D13: 127.8929 | E13: =IFERROR(C13/D13-1,"") | F13: 0.0059 | G13: 2026-09-18 | J13: Not publicly reported | K13: Available | L13: Available
A14: 46275 | B14: Thu | C14: 128.5 | D14: 127.8838 | E14: =IFERROR(C14/D14-1,"") | F14: 0.0059 | G14: 2026-09-18 | J14: Not publicly reported | K14: Available | L14: Available
A15: 46276 | B15: Fri | C15: 127.5 | D15: 126.8833 | E15: =IFERROR(C15/D15-1,"") | F15: 0.0059 | G15: 2026-09-18 | J15: Not publicly reported | K15: Available | L15: Available
A16: 46277 | B16: Sat | E16: =IFERROR(C16/D16-1,"") | F16: 0.0059 | G16: 2026-09-18 | J16: Not publicly reported | K16: No price observation retrieved | L16: No NAV observation in supplied extract
A17: 46278 | B17: Sun | E17: =IFERROR(C17/D17-1,"") | F17: 0.0059 | G17: 2026-09-18 | J17: Not publicly reported | K17: No price observation retrieved | L17: No NAV observation in supplied extract
A18: 46279 | B18: Mon | E18: =IFERROR(C18/D18-1,"") | F18: 0.0059 | G18: 2026-09-18 | J18: Not publicly reported | K18: No price observation retrieved | L18: No NAV observation in supplied extract
A19: 46280 | B19: Tue | C19: 126.05 | D19: 125.7118 | E19: =IFERROR(C19/D19-1,"") | F19: 0.0059 | G19: 2026-09-18 | J19: Not publicly reported | K19: Available | L19: Available
A20: 46281 | B20: Wed | C20: 127.15 | D20: 127.1966 | E20: =IFERROR(C20/D20-1,"") | F20: 0.0059 | G20: 2026-09-18 | J20: Not publicly reported | K20: Available | L20: Available
A21: 46282 | B21: Thu | C21: 126.85 | D21: 126.5533 | E21: =IFERROR(C21/D21-1,"") | F21: 0.0059 | G21: 2026-09-18 | J21: Not publicly reported | K21: Available | L21: Available
A22: 46283 | B22: Fri | C22: 128.6 | D22: 128.2152 | E22: =IFERROR(C22/D22-1,"") | F22: 0.0059 | G22: 2026-09-18 | J22: Not publicly reported | K22: Available | L22: Available
A23: 46286 | B23: Mon | C23: 127.9 | D23: 129.4092 | E23: =IFERROR(C23/D23-1,"") | F23: 0.0059 | G23: 2026-09-18 | J23: Available | K23: No price observation retrieved | L23: No NAV observation in supplied extract
A24: 46287 | B24: Tue | C24: 127.25 | D24: 128.7893 | J24: Available
A25: 46288 | B25: Wed | C25: 127.1 | D25: 128.4002 | J25: Available
A26: 46289 | B26: Thu | C26: 125.8 | D26: 127.3068 | J26: Available
A27: 46290 | B27: Fri | C27: 126.65 | D27: 128.3633 | J27: Available
A28: TER source
A29: TD source | B29: https://www.utimf.com/mutual-funds/uti-gold-exchange-traded-fund
A30: Market-price source | B30: https://finance.yahoo.com/quote/GOLDBETA.NS/history/

Sheet HDFCGOLD
A1: HDFC Gold ETF (HDFCGOLD.NS) — Daily Tracker
A3: Fund | B3: HDFC Gold ETF | D3: Notes | E3: Daily NAV values verified against the user-supplied HDFC Mutual Fund / AMFI extract: ₹129.2599 on 07-Sep-2026 through ₹130.1465 on 18-Sep-2026. Market close source: Yahoo Finance. TD values were not reliably reported.
A4: Yahoo symbol | B4: HDFCGOLD.NS
A5: TER (periodic) | B5: 0.006
A6: TER as of | B6: 2026-08-30
A7: TD 1Y (periodic)
A8: TD 3Y (periodic)
A9: TD as of | B9: Not publicly reported
A10: Date | B10: Day | C10: Market Close (₹) | D10: NAV (₹) | E10: Premium/(Discount) to NAV % | F10: TER % (periodic) | G10: TER As Of | H10: TD 1Y % (periodic) | I10: TD 3Y % (periodic) | J10: TD As Of | K10: Market Data Status | L10: NAV Data Status
A11: 46272 | B11: Mon | C11: 129.88 | D11: 129.2599 | E11: =IFERROR(C11/D11-1,"") | F11: 0.006 | G11: 2026-08-30 | J11: Not publicly reported | K11: Available | L11: Available
A12: 46273 | B12: Tue | C12: 130.18 | D12: 129.5903 | E12: =IFERROR(C12/D12-1,"") | F12: 0.006 | G12: 2026-08-30 | J12: Not publicly reported | K12: Available | L12: Available
A13: 46274 | B13: Wed | C13: 130.06 | D13: 129.8203 | E13: =IFERROR(C13/D13-1,"") | F13: 0.006 | G13: 2026-08-30 | J13: Not publicly reported | K13: Available | L13: Available
A14: 46275 | B14: Thu | C14: 130.49 | D14: 129.8157 | E14: =IFERROR(C14/D14-1,"") | F14: 0.006 | G14: 2026-08-30 | J14: Not publicly reported | K14: Available | L14: Available
A15: 46276 | B15: Fri | C15: 129.37 | D15: 128.7983 | E15: =IFERROR(C15/D15-1,"") | F15: 0.006 | G15: 2026-08-30 | J15: Not publicly reported | K15: Available | L15: Available
A16: 46277 | B16: Sat | E16: =IFERROR(C16/D16-1,"") | F16: 0.006 | G16: 2026-08-30 | J16: Not publicly reported | K16: No price observation retrieved | L16: Not available for this date
A17: 46278 | B17: Sun | E17: =IFERROR(C17/D17-1,"") | F17: 0.006 | G17: 2026-08-30 | J17: Not publicly reported | K17: No price observation retrieved | L17: Not available for this date
A18: 46279 | B18: Mon | E18: =IFERROR(C18/D18-1,"") | F18: 0.006 | G18: 2026-08-30 | J18: Not publicly reported | K18: No price observation retrieved | L18: Not available for this date
A19: 46280 | B19: Tue | C19: 127.88 | D19: 127.6122 | E19: =IFERROR(C19/D19-1,"") | F19: 0.006 | G19: 2026-08-30 | J19: Not publicly reported | K19: Available | L19: Available
A20: 46281 | B20: Wed | C20: 129.11 | D20: 129.1154 | E20: =IFERROR(C20/D20-1,"") | F20: 0.006 | G20: 2026-08-30 | J20: Not publicly reported | K20: Available | L20: Available
A21: 46282 | B21: Thu | C21: 128.68 | D21: 128.4641 | E21: =IFERROR(C21/D21-1,"") | F21: 0.006 | G21: 2026-08-30 | J21: Not publicly reported | K21: Available | L21: Available
A22: 46283 | B22: Fri | C22: 130.64 | D22: 130.1465 | E22: =IFERROR(C22/D22-1,"") | F22: 0.006 | G22: 2026-08-30 | J22: Not publicly reported | K22: Available | L22: Available
A23: 46286 | B23: Mon | C23: 129.83 | D23: 129.6745 | E23: =IFERROR(C23/D23-1,"") | F23: 0.006 | G23: 2026-08-30 | J23: Available | K23: No price observation retrieved | L23: Not available for this date
A24: 46287 | B24: Tue | C24: 129.26 | D24: 129.0517 | J24: Available
A25: 46288 | B25: Wed | C25: 128.94 | D25: 128.661 | J25: Available
A26: 46289 | B26: Thu | C26: 127.64 | D26: 127.5625 | J26: Available
A27: 46290 | B27: Fri | C27: 128.63 | D27: 128.625 | J27: Available
A28: TER source
A29: TD source | B29: https://www.hdfcfund.com/explore/mutual-funds/hdfc-gold-etf/regular
A30: Market-price source | B30: https://finance.yahoo.com/quote/HDFCGOLD.NS/history/

Sheet GOLDIETF
A1: ICICI Prudential Gold ETF (GOLDIETF.NS) — Daily Tracker
A3: Fund | B3: ICICI Prudential Gold ETF | D3: Notes | E3: Daily NAV values verified against the user-supplied ICICI Prudential Mutual Fund extract: ₹129.5659 on 07-Sep-2026 through ₹130.4544 on 18-Sep-2026. Market close source: Yahoo Finance. TER and TD are periodic AMC disclosures.
A4: Yahoo symbol | B4: GOLDIETF.NS
A5: TER (periodic) | B5: 0.0042
A6: TER as of | B6: 2026-08-31
A7: TD 1Y (periodic) | B7: -0.0165
A8: TD 3Y (periodic) | B8: -0.0137
A9: TD as of | B9: 2026-08-31
A10: Date | B10: Day | C10: Market Close (₹) | D10: NAV (₹) | E10: Premium/(Discount) to NAV % | F10: TER % (periodic) | G10: TER As Of | H10: TD 1Y % (periodic) | I10: TD 3Y % (periodic) | J10: TD As Of | K10: Market Data Status | L10: NAV Data Status
A11: 46272 | B11: Mon | C11: 130.01 | D11: 129.5659 | E11: =IFERROR(C11/D11-1,"") | F11: 0.0042 | G11: 2026-08-31 | H11: -0.0165 | I11: -0.0137 | J11: 2026-08-31 | K11: Available | L11: Available
A12: 46273 | B12: Tue | C12: 130.38 | D12: 129.8962 | E12: =IFERROR(C12/D12-1,"") | F12: 0.0042 | G12: 2026-08-31 | H12: -0.0165 | I12: -0.0137 | J12: 2026-08-31 | K12: Available | L12: Available
A13: 46274 | B13: Wed | C13: 130.37 | D13: 130.1261 | E13: =IFERROR(C13/D13-1,"") | F13: 0.0042 | G13: 2026-08-31 | H13: -0.0165 | I13: -0.0137 | J13: 2026-08-31 | K13: Available | L13: Available
A14: 46275 | B14: Thu | C14: 130.75 | D14: 130.1219 | E14: =IFERROR(C14/D14-1,"") | F14: 0.0042 | G14: 2026-08-31 | H14: -0.0165 | I14: -0.0137 | J14: 2026-08-31 | K14: Available | L14: Available
A15: 46276 | B15: Fri | C15: 129.63 | D15: 129.1065 | E15: =IFERROR(C15/D15-1,"") | F15: 0.0042 | G15: 2026-08-31 | H15: -0.0165 | I15: -0.0137 | J15: 2026-08-31 | K15: Available | L15: Available
A16: 46277 | B16: Sat | E16: =IFERROR(C16/D16-1,"") | F16: 0.0042 | G16: 2026-08-31 | H16: -0.0165 | I16: -0.0137 | J16: 2026-08-31 | K16: No price observation retrieved | L16: Not available for this date
A17: 46278 | B17: Sun | E17: =IFERROR(C17/D17-1,"") | F17: 0.0042 | G17: 2026-08-31 | H17: -0.0165 | I17: -0.0137 | J17: 2026-08-31 | K17: No price observation retrieved | L17: Not available for this date
A18: 46279 | B18: Mon | E18: =IFERROR(C18/D18-1,"") | F18: 0.0042 | G18: 2026-08-31 | H18: -0.0165 | I18: -0.0137 | J18: 2026-08-31 | K18: No price observation retrieved | L18: Not available for this date
A19: 46280 | B19: Tue | C19: 127.94 | D19: 127.9237 | E19: =IFERROR(C19/D19-1,"") | F19: 0.0042 | G19: 2026-08-31 | H19: -0.0165 | I19: -0.0137 | J19: 2026-08-31 | K19: Available | L19: Available
A20: 46281 | B20: Wed | C20: 129.44 | D20: 129.4246 | E20: =IFERROR(C20/D20-1,"") | F20: 0.0042 | G20: 2026-08-31 | H20: -0.0165 | I20: -0.0137 | J20: 2026-08-31 | K20: Available | L20: Available
A21: 46282 | B21: Thu | C21: 128.97 | D21: 128.7747 | E21: =IFERROR(C21/D21-1,"") | F21: 0.0042 | G21: 2026-08-31 | H21: -0.0165 | I21: -0.0137 | J21: 2026-08-31 | K21: Available | L21: Available
A22: 46283 | B22: Fri | C22: 131.16 | D22: 130.4544 | E22: =IFERROR(C22/D22-1,"") | F22: 0.0042 | G22: 2026-08-31 | H22: -0.0165 | I22: -0.0137 | J22: 2026-08-31 | K22: Available | L22: Available
A23: 46286 | B23: Mon | C23: 130.01 | D23: 127.749 | E23: =IFERROR(C23/D23-1,"") | F23: 0.0042 | G23: 2026-08-31 | H23: -0.0165 | I23: -0.0137 | J23: Available | K23: No price observation retrieved | L23: Not available for this date
A24: 46287 | B24: Tue | C24: 129.42 | D24: 127.1338 | J24: Available
A25: 46288 | B25: Wed | C25: 129.21 | D25: 126.7478 | J25: Available
A26: 46289 | B26: Thu | C26: 127.88 | D26: 125.6627 | J26: Available
A27: 46290 | B27: Fri | C27: 129.03 | D27: 126.7123 | J27: Available
A28: TER source
A29: TD source | B29: https://www.icicipruamc.com/blob/knowledgecentre/factsheet-passive/Passive.pdf
A30: Market-price source | B30: https://finance.yahoo.com/quote/GOLDIETF.NS/history/

Sheet BSLGOLDETF
A1: Aditya Birla Sun Life Gold ETF (BSLGOLDETF.NS) — Daily Tracker
A3: Fund | B3: Aditya Birla Sun Life Gold ETF | D3: Notes | E3: Daily NAV from official AMFI NAV history. TER 0.37% as of 2026-07-31. Public sources exposed tracking error, not retrievable TD values. Yahoo history: https://finance.yahoo.com/quote/BSLGOLDETF.NS/history/
A4: Yahoo symbol | B4: BSLGOLDETF.NS
A5: TER (periodic) | B5: 0.0037
A6: TER as of | B6: 2026-07-31
A7: TD 1Y (periodic)
A8: TD 3Y (periodic)
A9: TD as of | B9: Not publicly reported
A10: Date | B10: Day | C10: Market Close (₹) | D10: NAV (₹) | E10: Premium/(Discount) to NAV % | F10: TER % (periodic) | G10: TER As Of | H10: TD 1Y % (periodic) | I10: TD 3Y % (periodic) | J10: TD As Of | K10: Market Data Status | L10: NAV Data Status
A11: 46272 | B11: Mon | C11: 133.82 | D11: 133.0932 | E11: =IFERROR(C11/D11-1,"") | F11: 0.0037 | G11: 2026-07-31 | J11: Not publicly reported | K11: Available | L11: Available
A12: 46273 | B12: Tue | C12: 133.97 | D12: 133.4334 | E12: =IFERROR(C12/D12-1,"") | F12: 0.0037 | G12: 2026-07-31 | J12: Not publicly reported | K12: Available | L12: Available
A13: 46274 | B13: Wed | C13: 133.98 | D13: 133.6704 | E13: =IFERROR(C13/D13-1,"") | F13: 0.0037 | G13: 2026-07-31 | J13: Not publicly reported | K13: Available | L13: Available
A14: 46275 | B14: Thu | C14: 134.33 | D14: 133.6662 | E14: =IFERROR(C14/D14-1,"") | F14: 0.0037 | G14: 2026-07-31 | J14: Not publicly reported | K14: Available | L14: Available
A15: 46276 | B15: Fri | C15: 133.25 | D15: 132.6211 | E15: =IFERROR(C15/D15-1,"") | F15: 0.0037 | G15: 2026-07-31 | J15: Not publicly reported | K15: Available | L15: Available
A16: 46277 | B16: Sat | E16: =IFERROR(C16/D16-1,"") | F16: 0.0037 | G16: 2026-07-31 | J16: Not publicly reported | K16: No price observation retrieved | L16: Not available for this date
A17: 46278 | B17: Sun | E17: =IFERROR(C17/D17-1,"") | F17: 0.0037 | G17: 2026-07-31 | J17: Not publicly reported | K17: No price observation retrieved | L17: Not available for this date
A18: 46279 | B18: Mon | C18: 133.25 | E18: =IFERROR(C18/D18-1,"") | F18: 0.0037 | G18: 2026-07-31 | J18: Not publicly reported | K18: Available | L18: Not available for this date
A19: 46280 | B19: Tue | C19: 131.88 | D19: 131.4046 | E19: =IFERROR(C19/D19-1,"") | F19: 0.0037 | G19: 2026-07-31 | J19: Not publicly reported | K19: Available | L19: Available
A20: 46281 | B20: Wed | C20: 132.9 | D20: 132.9498 | E20: =IFERROR(C20/D20-1,"") | F20: 0.0037 | G20: 2026-07-31 | J20: Not publicly reported | K20: Available | L20: Available
A21: 46282 | B21: Thu | C21: 132.57 | D21: 132.2812 | E21: =IFERROR(C21/D21-1,"") | F21: 0.0037 | G21: 2026-07-31 | J21: Not publicly reported | K21: Available | L21: Available
A22: 46283 | B22: Fri | C22: 134.53 | D22: 134.0105 | E22: =IFERROR(C22/D22-1,"") | F22: 0.0037 | G22: 2026-07-31 | J22: Not publicly reported | K22: Available | L22: Available
A23: 46286 | B23: Mon | C23: 133.72 | D23: 133.5272 | E23: =IFERROR(C23/D23-1,"") | F23: 0.0037 | G23: 2026-07-31 | J23: Available | K23: No price observation retrieved | L23: Not available for this date
A24: 46287 | B24: Tue | C24: 133.06 | D24: 132.8879 | J24: Available
A25: 46288 | B25: Wed | C25: 132.9 | D25: 132.487 | J25: Available
A26: 46289 | B26: Thu | C26: 131.48 | D26: 131.3591 | J26: Available
A27: 46290 | B27: Fri | C27: 132.4 | D27: 132.4512 | J27: Available
A28: TER source
A29: TD source | B29: https://www.amfiindia.com/otherdata/tracking-error
A30: Market-price source | B30: https://finance.yahoo.com/quote/BSLGOLDETF.NS/history/

Sheet LICMFGOLD
A1: LIC MF Gold Exchange Traded Fund (LICMFGOLD.NS) — Daily Tracker
A3: Fund | B3: LIC MF Gold Exchange Traded Fund | D3: Notes | E3: Daily NAV values updated from the user-supplied LIC Mutual Fund / AMFI extract: ₹136.3462 on 07-Sep-2026 through ₹137.2833 on 18-Sep-2026. Market close source: Yahoo Finance. LIC snapshot reports TER as NA; TD values were not reliably reported.
A4: Yahoo symbol | B4: LICMFGOLD.NS
A5: TER (periodic)
A6: TER as of | B6: Not reliably reported
A7: TD 1Y (periodic)
A8: TD 3Y (periodic) | B8: Daily public series available (LIC Mutual Fund / AMFI extract supplied by user)
A9: TD as of | B9: Not publicly reported
A10: Date | B10: Day | C10: Market Close (₹) | D10: NAV (₹) | E10: Premium/(Discount) to NAV % | F10: TER % (periodic) | G10: TER As Of | H10: TD 1Y % (periodic) | I10: TD 3Y % (periodic) | J10: TD As Of | K10: Market Data Status | L10: NAV Data Status
A11: 46286 | B11: Mon | C11: 137.1 | D11: 136.3462 | E11: =IFERROR(C11/D11-1,"") | G11: Not reliably reported | J11: Not publicly reported | K11: Available | L11: Available
A12: 46273 | B12: Tue | C12: 137.2 | D12: 136.6939 | E12: =IFERROR(C12/D12-1,"") | G12: Not reliably reported | J12: Not publicly reported | K12: Available | L12: Available
A13: 46274 | B13: Wed | C13: 136.9 | D13: 136.936 | E13: =IFERROR(C13/D13-1,"") | G13: Not reliably reported | J13: Not publicly reported | K13: Available | L13: Available
A14: 46275 | B14: Thu | C14: 137.2 | D14: 136.9317 | E14: =IFERROR(C14/D14-1,"") | G14: Not reliably reported | J14: Not publicly reported | K14: Available | L14: Available
A15: 46276 | B15: Fri | C15: 136.3 | D15: 135.8635 | E15: =IFERROR(C15/D15-1,"") | G15: Not reliably reported | J15: Not publicly reported | K15: Available | L15: Available
A16: 46277 | B16: Sat | E16: =IFERROR(C16/D16-1,"") | G16: Not reliably reported | J16: Not publicly reported | K16: No price observation retrieved | L16: No NAV observation in supplied extract
A17: 46278 | B17: Sun | E17: =IFERROR(C17/D17-1,"") | G17: Not reliably reported | J17: Not publicly reported | K17: No price observation retrieved | L17: No NAV observation in supplied extract
A18: 46279 | B18: Mon | C18: 136.3 | E18: =IFERROR(C18/D18-1,"") | G18: Not reliably reported | J18: Not publicly reported | K18: Available | L18: No NAV observation in supplied extract
A19: 46280 | B19: Tue | C19: 133.95 | D19: 134.6196 | E19: =IFERROR(C19/D19-1,"") | G19: Not reliably reported | J19: Not publicly reported | K19: Available | L19: Available
A20: 46281 | B20: Wed | C20: 135.6 | D20: 136.1991 | E20: =IFERROR(C20/D20-1,"") | G20: Not reliably reported | J20: Not publicly reported | K20: Available | L20: Available
A21: 46282 | B21: Thu | C21: 135.3 | D21: 135.5155 | E21: =IFERROR(C21/D21-1,"") | G21: Not reliably reported | J21: Not publicly reported | K21: Available | L21: Available
A22: 46283 | B22: Fri | C22: 137.65 | D22: 137.2833 | E22: =IFERROR(C22/D22-1,"") | G22: Not reliably reported | J22: Not publicly reported | K22: Available | L22: Available
A23: 46286 | B23: Mon | C23: 136.45 | D23: 136.7891 | J23: Available
A24: 46287 | B24: Tue | C24: 135.8 | D24: 136.1354 | J24: Available
A25: 46288 | B25: Wed | C25: 135.9 | D25: 135.7255 | J25: Available
A26: 46289 | B26: Thu | C26: 134.5 | D26: 134.5721 | J26: Available
A27: 46290 | B27: Fri | C27: 135.7 | D27: 135.6887 | J27: Available
A28: TD source
A29: Market-price source | B29: https://finance.yahoo.com/quote/LICMFGOLD.NS/history/

Sheet Read Me
A1: Daily Gold ETF Price, NAV, TER and Tracking Difference Tracker
A3: Scope | B3: Date-wise tracker from 7-Sep-2026 through 21-Sep-2026 for the five allocated ETFs.
A4: Daily price | B4: Yahoo Finance historical market closing price, INR per ETF unit.
A5: Daily NAV | B5: Official/public historical NAV where available. For GOLDBETA and LICMFGOLD, only the latest publicly exposed NAV is entered; other dates are left blank.
A6: TER | B6: Periodic expense-ratio disclosure, repeated for reference with its reporting date. TER is not a daily market observation.
A7: Tracking difference | B7: Periodic disclosure, repeated for reference with its reporting date. Blank means no reliable public value was found; tracking error was not substituted.
A8: Non-trading days | B8: Rows are retained for date continuity; no market close/NAV is shown where no observation was retrieved.
A9: Data caveat | B9: This is a research tracker, not a broker ledger. Validate prices/NAV/TER/TD against official AMC/AMFI disclosures and contract notes before relying on it.
